{"id": "255d0ee0-7e0d-4262-4203-4b2d426b103a", "content": "Euronext estudia una opa sobre Bolsas y Mercados Espa\u00f1oles\n\nEl operador de Bolsa Euronext est\u00e1 estudiando lanzar una opa sobre Bolsas y Mercados Espa\u00f1oles, mientras busca acuerdos para crecer y entrar en nuevos mercados, seg\u00fan fuentes cercanas a la operaci\u00f3n. Seg\u00fan Bloomberg, Euronext \u2014gestor de mercados financieros de origen franc\u00e9s\u2014 ha valorado la idea de presentar una oferta por BME con diferentes asesores, seg\u00fan fuentes que pidieron el anonimato. Tambi\u00e9n estudian lanzar una oferta por la Bolsa de Mil\u00e1n, que ahora est\u00e1 en manos del London Stock Exchange Group.\nEl proveedor de servicios tecnol\u00f3gicos Refinitiv es due\u00f1o de los parqu\u00e9s de Londres y Mil\u00e1n, por lo que podr\u00eda tener que vender uno de ellos por problemas con las autoridades de Competencia. Euronext niega que est\u00e9 manteniendo conversaciones formales para realizar esta operaci\u00f3n.\nLas acciones de BME han subido casi un 10% en el \u00faltimo mes, con un valor de mercado de 2.100 millones de euros. Euronext, dirigido por el exbanquero de fusiones y adquisiciones Stephane Boujnah, no oculta que quiere realizar compras en toda Europa. La posibilidad de un movimiento en el sector se lleva hablando desde hace a\u00f1os, mientras Euronext crec\u00eda con las sucesivas compras: ya controla los parqu\u00e9s de Par\u00eds, Bruselas, \u00c1msterdam, Lisboa, Londres y Dubl\u00edn.\nLos analistas de Citigroup dijeron la semana pasada que Euronext tiene un \u201cflujo de efectivo impresionante\u201d, mientras que BME tiene pocas oportunidades de crecimiento. Los gestores de mercados est\u00e1n buscando acuerdos y operacioens que les permitan reducir su dependencia de los bajos m\u00e1rgenes que hay en las transacciones de t\u00edtulos burs\u00e1tiles. Deutsche B\u00f6rse, el propietario de la Bolsa de Fr\u00e1ncfort, que tiene unos 2.000 millones de euros presupuestados para hacer compras o fusionarse con otros operadores, lleg\u00f3 en abril a un acuerdo para adquirir Axioma. SIX, el operador suizo, tambi\u00e9n ha anunciado que est\u00e1 dispuesto a vender parte de su participaci\u00f3n en el proveedor franc\u00e9s de pagos para financiar otras adquisiciones.\n\u00a0\n NEWSLETTER \n Recibe la mejor informaci\u00f3n en tu bandeja de entrada \nAprovecha nuestro cup\u00f3n del 5%\nConsigue hasta un 50% de descuento\nConsigue un 10% de descuento\nAprovecha nuestro cup\u00f3n de 6\u20ac\nSi vas a contratar una hipoteca\n\u00a1No te las pierdas!\n\u00a1Desc\u00fabrelas!\nTe damos unos consejos\n\u00a1M\u00e1s por menos!\nSelecci\u00f3n de viviendas con dos plantas\nNo te pierdas nuestra selecci\u00f3n para terminar el a\u00f1o\nComedores para grandes familias\n\u00a1Lidera proyectos a nivel internacional!\n\u00a1Con 96% de descuento!\n\u00a1Escribe tu propia historia!\nExperto Universitario en Peritaje Inform\u00e1tico\nS\u00e1cale el m\u00e1ximo partido a tu voz con este curso 100% online\nFinancialo en c\u00f3modas cuotas\nCon 89% de descuento\nEstudia desde casa y a tu ritmo\nEl Valle de Zillertal es el para\u00edso de los deportes de invierno.\nValent\u00edn Dieste, nuestro experto, os acompa\u00f1a en este viaje. 1.610\u20ac/pers.\nRecorre Nueva Zelanda y los escenarios m\u00e1s emblem\u00e1ticos de la saga.\nLa joya oculta del asi\u00e1tico. 2.970\u20ac/pers.\nCuyo precio en Amazon no supera los 75 euros\nPara regalar en Navidad\nM\u00e1s vendidas en Amazon\nPara personas mayores por menos de 50 euros", "date": "11/06/2019, 20:01:45", "tags": ["Operaciones burs\u00e1tiles", "Bolsa", "Mercados financieros", "Empresas", "Europa", "Finanzas"], "newspaper": "elpais"}