{"id": "2c50dda7-6dd2-47c3-6624-6fbd84c28c60", "content": "El rey de Marruecos indulta a la periodista encarcelada por abortar\n\nEl rey de Marruecos, Mohamed VI, ha indultado a la periodista Hajar Raisuni, quien se encuentra en prisi\u00f3n desde el 31 de agosto, acusada de someterse a una operaci\u00f3n de aborto \u2014acusaci\u00f3n que ella niega\u2014 y de mantener relaciones fuera del matrimonio. Raisuni, de 28 a\u00f1os, fue condenada el pasado d\u00eda 1 a un a\u00f1o de c\u00e1rcel. Igualmente se encontraban presos su compa\u00f1ero sentimental, condenado a otro a\u00f1o, y el m\u00e9dico que le practic\u00f3 la operaci\u00f3n, castigado con dos a\u00f1os de c\u00e1rcel y otros dos de inhabilitaci\u00f3n profesional. El anestesista y la secretaria de la cl\u00ednica fueron condenados a un a\u00f1o de libertad condicional y ocho meses respectivamente. Todos ellos se beneficiar\u00e1n de la gracia real.\nUn comunicado del Ministerio de Justicia emitido el mi\u00e9rcoles por la tarde se\u00f1al\u00f3: \u201cLa gracia real se inscribe en el marco de la preocupaci\u00f3n del soberano por preservar el futuro de dos prometidos que pretend\u00edan fundar una familia, conforme en el respeto de los preceptos religiosos y de la ley, a pesar de los errores que hayan podido cometer\u201d.\nEn 2018 la justicia marroqu\u00ed proces\u00f3 a 14.503 personas por \u201clibertinaje\u201d, 3.048 por adulterio, 170 por homosexualidad y 73 por aborto. Ninguno de esos casos tuvo la repercusi\u00f3n que ha tenido la detenci\u00f3n de Raisuni. Desde un primer momento, sus allegados indicaron que la detenci\u00f3n de la periodista obedec\u00eda m\u00e1s a cuestiones pol\u00edticas que judiciales.\nRaisuni trabaja para el diario Ajbar al Yaum, una de las escasas publicaciones cr\u00edticas con la pol\u00edtica del Estado. El director y propietario del peri\u00f3dico, Taufic Buachr\u00edn, se encuentra preso desde 2018 y condenado a 12 a\u00f1os de c\u00e1rcel por varios delitos de \u00edndole sexual, entre ellos el de violaci\u00f3n.\nLa defensa de Buachr\u00edn tambi\u00e9n alega que se encuentra en la c\u00e1rcel por razones pol\u00edticas y rechaza las acusaciones. La reportera Raisuni, que apoy\u00f3 en su d\u00eda al director encarcelado, es sobrina de dos personajes muy conocidos y muy cr\u00edticos con el Estado marroqu\u00ed. Por un lado, su t\u00edo Hamed Raisuni es presidente de la Uni\u00f3n Mundial de Ulemas. Otro t\u00edo, Suleim\u00e1n Raisuni, es un reputado columnista de izquierdas que escribe en Ajbar al Yaum.\nAl margen de las posibles implicaciones pol\u00edticas, el caso de Raisuni desat\u00f3 una ola de protestas que tuvo una gran repercusi\u00f3n internacional. La cineasta Sonia Terrab y la escritora Leila Slimani redactaron un escrito firmado por 490 mujeres y hombres donde denunciaban la hipocres\u00eda moral y sexual del pa\u00eds y se declaraban \u201cfuera de la ley\u201d.\nEl citado manifiesto, que ocup\u00f3 la portada del diario Le Monde dec\u00eda: \u201cNosotros, ciudadanas y ciudadanos marroqu\u00edes, nos declaramos fuera de la ley. Violamos leyes injustas, obsoletas, que no tienen ninguna raz\u00f3n de ser. Nosotros hemos tenido relaciones sexuales fuera del matrimonio, hemos sufrido, practicado o sido c\u00f3mplices de un aborto. Hemos aprendido a fingir, a simular. \u00bfDurante cu\u00e1nto tiempo hemos de seguir as\u00ed?\u201d.\nEn un principio lo firmaron 490 personas, en alusi\u00f3n al n\u00famero de uno de los art\u00edculos del C\u00f3digo Penal que m\u00e1s limitan las libertades individuales. Pero el texto ha sido ya suscrito por 12.000 personas. El indulto del monarca se ha conocido dos d\u00edas despu\u00e9s de que los organizadores del manifiesto anunciaron que se iban a constituir como un Movimiento para abrir y mantener el debate sobre las libertades individuales.\nLa resonancia del caso Raisuni no se detuvo en Francia. El pasado 25 de septiembre el diario New York Times publicaba un art\u00edculo de opini\u00f3n firmado por Ursula Lindsey en el que afirmaba: \u201cEl poder real en Marruecos yace casi enteramente en manos del rey, de su s\u00e9quito y del aparato de seguridad, no de los funcionarios electos. El Palacio posee el poder pol\u00edtico para reformar leyes retr\u00f3gradas. En cambio, las autoridades fomentan el conservadurismo social casi tanto como los islamistas, porque la piedra angular de ese conservadurismo es el respeto hacia la autoridad masculina\".\n NEWSLETTER \n Recibe el bolet\u00edn de Internacional \nUna breve gu\u00eda para que el hombre moderno (o sea, t\u00fa) sepa c\u00f3mo regalar joyas estas navidades evitando compras fallidas de \u00faltima hora y triste desaciertos. Si ya no triunfas regalando, es porque no quieres", "date": "10/16/2019, 19:01:45", "tags": ["Aborto ilegal", "Mohamed VI de Marruecos", "Indulto", "Marruecos", "Magreb", "Beneficios penitenciarios", "\u00c1frica", "R\u00e9gimen penitenciario", "Delitos", "Justicia"], "newspaper": "elpais"}