{"id": "511113e0-8e70-453c-4d81-97993f1da378", "content": "Boricua\n\nEn 2015 me invitaron a la Universidad de Puerto Rico. Conoc\u00ed a escritoras y docentes, combativas, Sof\u00eda Irene Cardona y Vanessa Vilches. El alumnado recaud\u00f3 fondos para sufragar mis dietas. Mis anfitrionas, mientras pase\u00e1bamos por San Juan, me hablaron de la corrupci\u00f3n y las precariedades de un pa\u00eds para el que un sector importante de la poblaci\u00f3n reclama independencia. \u201cUn pa\u00eds que estamos invent\u00e1ndonos\u201d, escribe Sof\u00eda. Mis amigas han salido a la calle muchas veces para reivindicar la gratuidad de la educaci\u00f3n, libertad de expresi\u00f3n y asociaci\u00f3n, un sistema de salud digno, el aborto o el retiro. Tambi\u00e9n han participado en las protestas contra el gobernador Ricardo Rossell\u00f3, que culminaron con su dimisi\u00f3n. En una tribuna de este peri\u00f3dico H\u00e9ctor Feliciano colocaba el foco en el lugar oportuno: \u201cLo que importa es saber (\u2026) qu\u00e9 camino tomar\u00e1 la lenta desintegraci\u00f3n del r\u00e9gimen colonial, (\u2026) si se propondr\u00e1n pol\u00edticas actualizadas de renovaci\u00f3n, nuevas formas de fiscalizar, si se idear\u00e1 una sociedad de derechos plenos\u2026\u201d. El escritor barajaba la posibilidad de un desenlace lampedusiano.\nEl que todo cambie para que todo siga igual ser\u00eda sangrante si consideramos que en Puerto Rico la violencia de Estado cobra forma de pelotas de goma y gas pimienta. Macana. El informe Km O, que se actualiza como documento vivo de una represi\u00f3n viva, acumulaba a primeros de agosto 70 p\u00e1ginas de denuncias por agresiones, abusos, maltrato policial, vulneraci\u00f3n de la libertad de expresi\u00f3n y derechos b\u00e1sicos de los manifestantes, detenciones ilegales y falsas detenciones publicitadas como ejemplar trabajo policial. Amnist\u00eda Internacional Puerto Rico, Brigada Legal Solidaria, Colegio de Abogados y Abogadas de Puerto Rico e Instituto Caribe\u00f1o de Derechos Humanos avalan los datos. A mis amigas les preocupa \u2014no tienen miedo\u2014 la integridad f\u00edsica de j\u00f3venes manifestantes. \u201c\u00a1Y tambi\u00e9n de las viejitas!\u201d, aclara Sof\u00eda: una sexagenaria ha sido detenida por llamar corrupto a Jorge Rashke, religioso derechista asociado a los pol\u00edticos proestadidad. All\u00e1 quieren vivir los cambios con alegr\u00eda y esperanza: \u201cLos ap\u00f3stoles de la prudencia llaman a no idealizar el movimiento que en 12 d\u00edas destituy\u00f3 al gobernador. Que no cantemos victoria, advierten cautelosos. Bendito, se\u00f1ores, no sean tan aguacatones\u201d, escribe Ana Lydia Vega. La repercusi\u00f3n de las protestas en Estados Unidos \u2014especialmente en el programa de la CBS de David Begnaud\u2014 sintoniza con el malestar por la incitaci\u00f3n al odio y la xenofobia trumpianas que desencadenan masacres como la de El Paso. Pese a que la protesta se pueda transformar en algo trendy, muchos y muchas agradecen la visibilidad otorgada por Ricky Martin o Bad Bunny. Yo, menos colonizada por Estados Unidos, pero no completamente descolonizada \u2014trendy, show business, Casual Friday, Facebook, Wall Street, Cuando Harry encontr\u00f3 a Sally\u2026\u2014 sigo con la duda de si solo por el glamur vemos los horrores o el glamur los emborrona convirtiendo en ef\u00edmera una lucha larga en la que no deber\u00edamos olvidar el v\u00ednculo entre historia, econom\u00eda, pol\u00edtica y cultura, que define la violencia de las dominaciones coloniales. \u201c\u00a1Ay, Santo, todo es Disneylandia!\u201d, dice Sof\u00eda Irene. Creo que el gesto del artista-ciudadano Martin es de agradecer, pero me preocupa la reducci\u00f3n a espect\u00e1culo de la pol\u00edtica. Mientras tanto, en San Juan, M\u00f3nica Flores sigue recibiendo golpes y Sof\u00eda, ante el nombramiento de nuevos gobernadores y gobernadoras, tiene preparadas las cacerolas.\nPuedes seguir EL PA\u00cdS Opini\u00f3n en Facebook, Twitter o suscribirte aqu\u00ed a la Newsletter.\n NEWSLETTER \n Recibe el bolet\u00edn de Opini\u00f3n \nUna breve gu\u00eda para que el hombre moderno (o sea, t\u00fa) sepa c\u00f3mo regalar joyas estas navidades evitando compras fallidas de \u00faltima hora y triste desaciertos. Si ya no triunfas regalando, es porque no quieres\nINICIA SESI\u00d3N PARA SEGUIR LEYENDO\nSolo con tener una cuenta ya puedes leer este art\u00edculo, es gratis.\nGracias por leer EL PA\u00cdS\n\u00bfNo est\u00e1s registrado? Crea tu cuenta", "date": "08/12/2019, 19:01:45", "tags": ["Opini\u00f3n", "Referencias El Pa\u00eds", "Crisis econ\u00f3mica", "El Pa\u00eds", "Puerto Rico", "Globalizaci\u00f3n", "Libertad expresi\u00f3n", "Xenofobia", "Coyuntura econ\u00f3mica", "Estados Unidos", "Discriminaci\u00f3n", "Am\u00e9rica", "Prejuicios", "Econom\u00eda", "Educaci\u00f3n", "Problemas sociales", "Sociedad"], "newspaper": "elpais"}