{"id": "51dd2403-095a-4498-53ed-76198f95bf66", "content": "Dos detenidos por la muerte de un peregrino alem\u00e1n\n\nLa Polic\u00eda Nacional ha detenido a dos hombres, de 34 y 20 a\u00f1os, por la agresi\u00f3n a un peregrino alem\u00e1n que provoc\u00f3 su muerte el pasado 25 de agosto. Ambos han sido puestos a disposici\u00f3n judicial y se enfrentan a una acusaci\u00f3n de homicidio.\nLos hechos se remontan al d\u00eda 12 de agosto, cuando el alem\u00e1n Bj\u00f6rn Hoffan, que estaba en Pontevedra haciendo el Camino de Santiago, sali\u00f3 de noche con unos amigos y fue agredido cerca de un bar. La v\u00edctima, de 42 a\u00f1os, qued\u00f3 inconsciente por los golpes en la cabeza, pero se neg\u00f3 a ser asistido por los m\u00e9dicos. Diez horas despu\u00e9s, comenz\u00f3 a sentirse mal y sus compa\u00f1eros lo llevaron a un centro de salud. Fue trasladado por una ambulancia al Hospital Montecelo de Pontevedra y, posteriormente, ante la gravedad de sus lesiones, al Hospital \u00c1lvaro Cunqueiro de Vigo, donde falleci\u00f3.\nLa Polic\u00eda ha reconstruido la agresi\u00f3n gracias a la declaraci\u00f3n de 20 testigos presentes en el momento. Con ello, han podido detener a los presuntos culpables, vecinos de Pontevedra y Mar\u00edn y con antecedentes policiales previos.\n NEWSLETTER \n Recibe el bolet\u00edn de Actualidad \nAprovecha nuestro cup\u00f3n del 5%\nConsigue hasta un 50% de descuento\nConsigue un 10% de descuento\nAprovecha nuestro cup\u00f3n de 6\u20ac\nSi vas a contratar una hipoteca\n\u00a1No te las pierdas!\n\u00a1Desc\u00fabrelas!\nTe damos unos consejos\n\u00a1M\u00e1s por menos!\nSelecci\u00f3n de viviendas con dos plantas\nNo te pierdas nuestra selecci\u00f3n para terminar el a\u00f1o\nComedores para grandes familias\n\u00a1Lidera proyectos a nivel internacional!\n\u00a1Con 96% de descuento!\n\u00a1Escribe tu propia historia!\nExperto Universitario en Peritaje Inform\u00e1tico\nS\u00e1cale el m\u00e1ximo partido a tu voz con este curso 100% online\nFinancialo en c\u00f3modas cuotas\nCon 89% de descuento\nEstudia desde casa y a tu ritmo\nEl Valle de Zillertal es el para\u00edso de los deportes de invierno.\nValent\u00edn Dieste, nuestro experto, os acompa\u00f1a en este viaje. 1.610\u20ac/pers.\nRecorre Nueva Zelanda y los escenarios m\u00e1s emblem\u00e1ticos de la saga.\nLa joya oculta del asi\u00e1tico. 2.970\u20ac/pers.\nCuyo precio en Amazon no supera los 75 euros\nPara regalar en Navidad\nM\u00e1s vendidas en Amazon\nPara personas mayores por menos de 50 euros", "date": "09/11/2019, 19:01:45", "tags": ["Pontevedra", "Camino de Santiago", "Agresiones f\u00edsicas", "Peregrinaciones", "Integridad personal", "Galicia", "Delitos", "Sucesos", "Espa\u00f1a", "Justicia"], "newspaper": "elpais"}