{"id": "721f52cf-1565-478a-5c49-9f17f709e165", "content": "La memoria de V\u00edctor Cabedo en la salida de la Vuelta en Onda\n\nRigo Ur\u00e1n espera en una UCI de un hospital de Barcelona que su organismo se recupere para poder operar sus huesos, rotos el jueves.\nEl pelot\u00f3n desciende entre quebradas y barrancos del Maestrazgo seco. Una curva se cierra m\u00e1s de lo esperado, un equipo se cierra, los ciclistas forman un acorde\u00f3n s\u00fabito que se abre y se cierra de lado a lado, incontrolado. Al fondo de la ca\u00edda inevitable, Rigo. Su hombro izquierdo, que recibi\u00f3 el impacto del asfalto se ha destrozado; en varios pedazos, alrededor de una placa met\u00e1lica, recuerdo de otra fractura antigua, se pulveriza la clav\u00edcula, y tambi\u00e9n la esc\u00e1pula; Las costillas no resisten el peso de bicis y compa\u00f1eros que se amontonan encima, y ceden, y tocan los pulmones. Los que han ca\u00eddo y pueden seguir se levantan r\u00e1pido y contin\u00faan; los que no, aceleran a su lado para no perder rueda sin siquiera mirar el desastre. La indiferencia estremece.\n\u201c\u00bfIndiferencia?; en absoluto, necesidad\u201d, dice \u00d3scar Cabedo, ciclista del Burgos. \u201cEs una imposici\u00f3n, una insensibilidad exterior a la que te fuerzas, porque ves la ca\u00edda y sufres por los que est\u00e1n ah\u00ed, y entiendes que el ciclismo es as\u00ed, en una nada pasas de volar a d\u00e1rtela, pero si pensaras que te puede pasar a ti ni siquiera montar\u00edas en bicicleta\u201d.\nLa etapa sale de Onda, chimeneas de cer\u00e1micas en el horizonte, en Castell\u00f3n, el pueblo de \u00d3scar y de su hermano Jos\u00e9, el director de su equipo. Los corredores firman antes de salir en un estrado alzado justo delante de un pabell\u00f3n polideportivo llamado V\u00edctor Cabedo Card\u00e1, en honor de su hermano, tambi\u00e9n ciclista, que muri\u00f3 hace siete a\u00f1os cuando un coche le mand\u00f3 por un barranco de la sierra de Espad\u00e1n, cerca de su pueblo, mientras se entrenaba.\nTen\u00eda 23 a\u00f1os. Corr\u00eda en el Euskadi. Era de la generaci\u00f3n de Mikel Landa y se le auguraba un futuro al menos tan espl\u00e9ndido como al alav\u00e9s. \u201cCuando el muri\u00f3 yo ten\u00eda 17 a\u00f1os y no montaba en bicicleta a\u00fan, y le admiraba por su meticulosidad, porque despu\u00e9s de cada entrenamiento volcaba todos los datos en el ordenador y se tiraba media hora analiz\u00e1ndolos y compar\u00e1ndolos con los de otros d\u00edas\u201d, dice \u00d3scar, quien se hizo ciclista en cierta medida por su deseo de terminar lo que su hermano hab\u00eda dejado a medias. \u201cS\u00ed, un poco eso, y tambi\u00e9n porque somos una familia ciclista, mis padres, mis hermanos, todos\u201d. Y est\u00e1 un poco nervioso, y emocionado, y su hermano, el hermano mayor, el director, porque salen de su pueblo, y est\u00e1n orgullosos. \u201cVemos todos los d\u00edas el nombre y la foto de nuestro hermano en el pabell\u00f3n, y m\u00e1s que hacernos pensar en \u00e9l, que ya pensamos cada minuto sin necesidad de ver su foto, nos emociona pensar que todos los chavales del pueblo sabr\u00e1n qui\u00e9n es y su vida, y siempre estar\u00e1 en el recuerdo de todos\u201d, dice Jos\u00e9, que como ciclista lleg\u00f3 a amateur y lo dej\u00f3. Durante la etapa, Jos\u00e9, con el coche, y \u00d3scar, en bicicleta, vuelven a pasar por las carreteras en las que se hicieron ciclistas, en las que muri\u00f3 su hermano. \u00d3scar sue\u00f1a con volar y llegar destacado, y alg\u00fan d\u00eda puede que lo logre, pero tambi\u00e9n sabe que puede que no. \u201cLos sue\u00f1os son muy dif\u00edciles de alcanzar\u201d, dice, y pedalea.\nPuedes seguir Deportes de EL PA\u00cdS en Facebook, Twitter o suscribirte aqu\u00ed a la Newsletter.\n NEWSLETTER \n Recibe el bolet\u00edn de Deportes \nUna breve gu\u00eda para que el hombre moderno (o sea, t\u00fa) sepa c\u00f3mo regalar joyas estas navidades evitando compras fallidas de \u00faltima hora y triste desaciertos. Si ya no triunfas regalando, es porque no quieres", "date": "08/30/2019, 19:01:45", "tags": ["Burgos-BH", "Vuelta Espa\u00f1a", "Equipo ciclista", "Vueltas ciclistas", "Ciclismo", "Equipos", "Competiciones", "Deportes"], "newspaper": "elpais"}