{"id": "8a020ce0-2863-4488-4696-dbafc3d44144", "content": "Marcel Proust sin las muchachas en flor\n\nMi destino era el Gran Hotel de Cabourg, en Normand\u00eda. Despu\u00e9s de atravesar colinas de jugosos pastos pobladas de vacas h\u00famedas hice un alto en Rouen para rendir homenaje a Gustave Flaubert y en su honor en una terraza frente a la catedral, que un d\u00eda pint\u00f3 Monet, me tom\u00e9 un calvados fabricado con manzanas benedictinas. Cualquiera de aquellas se\u00f1oras provincianas que cruzaban la plaza pod\u00eda haber sido Madame Bovary. Luego en la larga bajamar de la playa de Deauville galopaban jinetes contra la puesta de sol y bajo las sombrillas de color naranja hab\u00eda ba\u00f1istas rodeadas de ni\u00f1os rubios y perros hermosos. Al pasar por Honfleur record\u00e9 al m\u00fasico Erik Satie. Finalmente, a orillas de un mar brumoso estaba el establecimiento de ba\u00f1os, el Gran Hotel de Cabourg, el Balbec de En busca del tiempo perdido, de Marcel Proust.\nEra un ni\u00f1o asm\u00e1tico con sombrerito blanco de paja dura cuando Marcel Proust lleg\u00f3 por primera vez aqu\u00ed en 1881 llevado de la mano de su abuela y la criada Fran\u00e7oise. Durante su adolescencia y madurez, hasta 1914, nunca dej\u00f3 de pasar temporadas de verano en este hotel de Cabourg. Tendido en una cama con dosel, muerto de melancol\u00eda, desde su habitaci\u00f3n o\u00eda al atardecer una orquestina de pistones que tocaba valses en el templete de la m\u00fasica. Por el paseo de la playa discurr\u00edan las muchachas en flor, Albertina, Andr\u00e9e, Gis\u00e8le, Rosemunde, de trenzas y mejillas doradas.\nA la hora de la cena bajaba al comedor convertido en un maravilloso acuario, y all\u00ed arist\u00f3cratas y burgueses anillados, damas con pamelas de frutas y ni\u00f1as con muchos lazos, se mec\u00edan como extra\u00f1os peces y crust\u00e1ceos con una fosforescencia submarina. Amparados en la oscuridad de la noche, los pescadores y los obreros del pueblo pegaban la nariz a las vidrieras para contemplar la vida lujosa de esta fauna acu\u00e1tica y tal vez algunos ya dudaban si la pared de cristal proteger\u00eda por siempre aquel fest\u00edn. No fue la ira social de la pobre gente la que invadir\u00eda aquella pecera sino la oleada de sangre de la Gran Guerra del 14 y despu\u00e9s la lluvia de acero del desembarco de Normand\u00eda de las tropas aliadas de la Segunda Guerra Mundial. Cuando llegu\u00e9 el asalto corr\u00eda a cargo de un centenar de ejecutivos de una multinacional de inform\u00e1tica que hab\u00eda invadido la pecera, cada uno detr\u00e1s de un ordenador en mesas formando una herradura, llenas de carpetas, atentos a una gran pantalla que manipulaba un monitor.\nPero el ectoplasma de Proust parec\u00eda vagar todav\u00eda por las estancias y aposentos, por las salas de juego, los espacios de baile, el antiguo teatro del casino, las casetas de ba\u00f1o azules y blancas de la playa. En el mostrador de recepci\u00f3n hab\u00eda un busto del escritor. Un ejecutivo rezagado, mientras la recepcionista le abr\u00eda la ficha, se entreten\u00eda acariciando con la yema de los dedos el bigote y la orqu\u00eddea de bronce oscuro de ese busto cuyo nombre ignoraba.\n\u2014Es Marcel Proust. Lo pone ah\u00ed, en el pedestal\u2014 le sac\u00f3 de dudas la recepcionista.\n\u2014El fundador de este establecimiento. \u00bfMe equivoco?\n\u2014Perd\u00f3n. Marcel Proust fue un escritor muy famoso.\n\u2014Disc\u00falpeme, se\u00f1orita. Yo soy t\u00e9cnico en ordenadores. Uno se pasa el d\u00eda vendiendo m\u00e1quinas. Veo que he metido la pata.\n\u2014No, por Dios.\n\u2014\u00bfEscribi\u00f3 algo importante este se\u00f1or?\n\u2014Confieso que tampoco le he le\u00eddo nada\u2014 respondi\u00f3 la recepcionista\u2014 Lo tenemos aqu\u00ed porque fue un buen cliente del hotel. Creo que escribi\u00f3 la historia de una magdalena.\n\u2014\u00bfAh, s\u00ed? Precisamente, se\u00f1orita, yo acabo de informatizar una vieja f\u00e1brica de galletas, magdalenas y bizcochos para ponerla al d\u00eda.\n\u2014\u00a1Qu\u00e9 casualidad! Tome la llave, se\u00f1or. Habitaci\u00f3n 216. Tiene una magn\u00edfica vista al mar. Bienvenido.\nEl hotel conservaba el esplendor decadente adherido a los espejos biselados, a los frescos con ninfas danzantes, a las cortinas de terciopelo verde manzana. En la pecera del comedor los antiguos crust\u00e1ceos, que eran arist\u00f3cratas y burgueses de entreguerras, hab\u00edan sido suplantados por ejecutivos, programadores y vendedores inform\u00e1ticos, quienes despu\u00e9s de cada sesi\u00f3n de trabajo invad\u00edan los salones y no paraban de soltar carcajadas sobre las floridas alfombras; repantingados en los canap\u00e9s con un licor en la mano segu\u00edan con ojos golosos a las chicas de carnes mesocr\u00e1ticas que cruzaban en bikini por el sal\u00f3n, aunque ninguna era ya Albertina, ni Andr\u00e9e, ni Gis\u00e8le ni Rosemunde, aquellas muchachas en flor desaparecidas junto con el fantasma de Proust.", "date": "08/31/2019, 19:01:45", "tags": ["Marcel Proust", "Libros", "Cultura"], "newspaper": "elpais"}