{"id": "8ccca586-f951-4826-62b5-a732bcfddfdd", "content": "Homenajes a las v\u00edctimas de Dayton y El Paso, en im\u00e1genes\n", "date": "08/05/2019, 19:01:45", "tags": ["Ohio", "Control armas", "Armamento", "Defensa", "Terrorismo", "Matanza El Paso", "Patrick Crusius", "Tiroteos", "El Paso", "Texas ", "Incidentes", "Estados Unidos", "Asesinatos m\u00faltiples", "Racismo", "Norteam\u00e9rica", "Asesinatos", "Delitos odio", "Discriminaci\u00f3n", "Am\u00e9rica", "Prejuicios", "Sucesos", "Delitos", "Problemas sociales", "Sociedad", "Justicia"], "newspaper": "elpais"}