{"id": "8dee5f22-1052-45a9-5cf1-bef3662930fb", "content": "La Reina y do\u00f1a Sof\u00eda con Leonor y Sof\u00eda, en el cine para ver \u2018El rey Le\u00f3n\u2019\n\nLa reina Letizia junto a sus hijas, la princesa Leonor y la infanta Sof\u00eda, acudieron acompa\u00f1adas por do\u00f1a Sof\u00eda a ver la pel\u00edcula El Rey Le\u00f3n en el c\u00e9ntrico cine R\u00edvoli de Palma en la tarde de este jueves. En su primer d\u00eda de vacaciones en la isla las cuatro se dejaron ver llegando juntas a la sala de cine para ver uno de los estrenos del verano y despu\u00e9s recorrieron la peatonal calle Blanquerna, plagada de tiendas y restaurantes, antes de subir al coche que les llev\u00f3 de regreso al palacio de Marivent.\nLa Reina em\u00e9rita ya acudi\u00f3 el pasado martes a ver la misma pel\u00edcula en esta sala de cine con sus nietas Victoria Federica e Irene, que como ya es tradicional pasan estos d\u00edas de verano en la isla con su abuela y algunos de sus primos. Sin embargo, la reina Letizia y sus hijas llegaron a Palma la tarde del mi\u00e9rcoles y el jueves por la ma\u00f1ana acudieron al Real Club N\u00e1utico de Palma para acompa\u00f1ar a Felipe VI en la jornada de regatas de la Copa del Rey de Vela que se disputa en aguas de la bah\u00eda. Los cuatro miembros de la familia posaron en las escaleras de entrada del club en su primera aparici\u00f3n juntos en la isla este verano.\nLa salida de las reinas junto a Leonor y Sof\u00eda, que fue recogida por numerosos fot\u00f3grafos, recuerda a la visita al mercado del Olivar que realizaron el verano pasado y que intent\u00f3 acallar los rumores de distanciamiento entre suegra y nuera destapados tras el encontronazo que mantuvieron a cuenta de una fotograf\u00eda a las puertas de la catedral de Mallorca durante la misa de Pascua de 2018. El que estaba llamado a ser el acto para escenificar el regreso del rey em\u00e9rito a las actividades p\u00fablicas de la familia real qued\u00f3 eclipsado por el rifirrafe entre la reina Letizia y do\u00f1a Sof\u00eda.\nLa agenda oficial de la familia real en Mallorca estas vacaciones continuar\u00e1 el s\u00e1bado con la entrega de los premios de la Copa del Rey por parte de don Felipe. Est\u00e1 previsto que el domingo tenga lugar el tradicional posado veraniego de los reyes con sus hijas, mientras que el lunes podr\u00edan desarrollarse las audiencias que Felipe VI ofrece a las principales autoridades de las islas. El mi\u00e9rcoles, los reyes han convocado en el palacio de la Almudaina a los principales representantes de la sociedad balear, as\u00ed como a los actores pol\u00edticos y autoridades para la recepci\u00f3n que sustituy\u00f3 a la cena de gala ofrecida por don Juan Carlos y do\u00f1a Sof\u00eda. Ese mismo d\u00edas est\u00e1 previsto que Felipe VI despache con el presidente del Gobierno en funciones, Pedro S\u00e1nchez, en el palacio de Marivent.\nLa Reina em\u00e9rita fue la primera en aterrizar en la isla. El jueves de la semana pasada acudi\u00f3 a visitar la embarcaci\u00f3n cient\u00edfica Toftevaag que realiza labores de limpieza de micropl\u00e1sticos y basura en el mar dentro del proyecto Libera. El viernes acudi\u00f3 con el rey em\u00e9rito a visitar la academia de tenis de Rafael Nadal en Manacor. La visita fue de car\u00e1cter privado, aunque ambos estuvieron guiados en todo momento por el tenista y su novia, Mar\u00eda Francisca Perell\u00f3. Despu\u00e9s, junto a los padres de ambos, acudieron a comer a un restaurante de la zona. Por el momento, se desconoce si todos los nietos de la reina em\u00e9rita coincidir\u00e1n estos d\u00edas en Palma.\n NEWSLETTER \n Recibe la mejor informaci\u00f3n en tu bandeja de entrada \nUna breve gu\u00eda para que el hombre moderno (o sea, t\u00fa) sepa c\u00f3mo regalar joyas estas navidades evitando compras fallidas de \u00faltima hora y triste desaciertos. Si ya no triunfas regalando, es porque no quieres", "date": "08/02/2019, 19:01:45", "tags": ["Leonor de Borb\u00f3n", "Sofia de Borb\u00f3n", "Reina Letizia", "Palma", "Vacaciones Reales", "Gente", "Princesa de Asturias", "Mallorca", "Realeza", "Famosos", "Pel\u00edculas", "Baleares", "Familia Real", "Casa Real", "Cine", "Espa\u00f1a", "Pol\u00edtica"], "newspaper": "elpais"}