{"id": "9cfe52fa-7bba-4b65-6041-d60d99288ee4", "content": "Los avances en la esperanza de vida se ralentizan en la OCDE\n\nLos avances en esperanza de vida que se han sucedido de forma casi ininterrumpida durante d\u00e9cadas se est\u00e1n ralentizando en la Organizaci\u00f3n para la Cooperaci\u00f3n y el Desarrollo Econ\u00f3mico (OCDE) a causa de la obesidad, la diabetes, el envejecimiento de la poblaci\u00f3n o el consumo de opi\u00e1ceos, que en Estados Unidos ha contribuido a un inquietante retroceso. Y en esos cinco \u00faltimos a\u00f1os Estados Unidos fue el \u00fanico pa\u00eds de la OCDE donde la esperanza de vida descendi\u00f3 (2,4 meses).\u00a0En su informe anual sobre la salud y los sistemas sanitarios publicado este jueves, la organizaci\u00f3n indica cu\u00e1les eran los pa\u00edses con mayor esperanza de vida en 2017: Jap\u00f3n (84,2 a\u00f1os), Suiza (83,6), Espa\u00f1a (83,4) e Italia (83).\nEsos cuatro pa\u00edses est\u00e1n netamente por encima de la media de 80,7 a\u00f1os y, sobre todo, lejos de los que cierran la lista: Lituania (75,4 a\u00f1os), M\u00e9xico (74,8) y Letonia (74,6). Los progresos han sido significativos desde 1970 en todos los miembros de la organizaci\u00f3n, y en particular en Turqu\u00eda (24 a\u00f1os), Corea del Sur (20) y Chile (18), pero la situaci\u00f3n est\u00e1 cambiando, sobre todo en Estados Unidos, Francia, Holanda, Alemania y el Reino Unido.\u00a0El incremento entre 2002 y 2007 fue de media de 22,8 meses en la OCDE, pero se qued\u00f3 en 11,2 meses entre 2012 y 2017.\nDetr\u00e1s est\u00e1n la creciente epidemia de obesidad y la diabetes, pero tambi\u00e9n menos mejoras en el tratamiento de enfermedades coronarias y derrames cerebrales, as\u00ed como el progresivo envejecimiento de la poblaci\u00f3n, que hace m\u00e1s dif\u00edcil elevar los a\u00f1os de vida. Puntualmente, ha habido brotes de enfermedades respiratorias durante los a\u00f1os de referencia, y en particular la gripe que afect\u00f3 a Europa en 2015 y que caus\u00f3 una ca\u00edda de la esperanza de vida en 19 de los 36 miembros de la OCDE. A todo eso se a\u00f1ade la crisis de los opi\u00e1ceos, particularmente grave en EE UU, donde desde 2011 ha estado en el origen de unas 400.000 muertes.\nLa tendencia reciente de ralentizaci\u00f3n de la esperanza de vida ha tenido algunas excepciones, sobre todo en Turqu\u00eda, Chile, Lituania y M\u00e9xico. Las menores tasas de mortalidad evitable (por prevenci\u00f3n o por tratamiento) en la OCDE se constatan en Suiza, Islandia, Jap\u00f3n, Suecia y Noruega. Las peores, en M\u00e9xico, Letonia, Hungr\u00eda y Lituania.\nEntre los principales factores de riesgo est\u00e1 el tabaquismo, que aunque ha disminuido es un h\u00e1bito diario para el 18% de la poblaci\u00f3n en el conjunto de la OCDE y para m\u00e1s del 25% de los mayores de 15 a\u00f1os en Francia, Hungr\u00eda, Turqu\u00eda y Grecia. Tambi\u00e9n el alcohol, con un consumo medio de 8,9 litros de alcohol puro al a\u00f1o y m\u00e1s de 11 en Hungr\u00eda, Luxemburgo, Irlanda, Francia, Austria, Rep\u00fablica Checa, Francia, Letonia y Lituania. El sobrepeso concierne al 55,6% de los adultos en la OCDE y supera el 70% en Estados Unidos, M\u00e9xico y Chile, mientras que afecta a menos del 35% en Corea del Sur y Jap\u00f3n.\nLa contaminaci\u00f3n atmosf\u00e9rica provoca una media de 39,6 fallecimientos anuales por cada 100.000 habitantes, pero m\u00e1s de 75 en Grecia, Polonia, Lituania, Hungr\u00eda y Letonia, y menos de 20 en Australia, Canad\u00e1, Finlandia, Islandia, Noruega, Nueva Zelanda y Suecia.\nAunque por regla general los pa\u00edses que m\u00e1s gastan en sanidad y aquellos cuyo sistema sanitario tiene m\u00e1s personal y recursos son los que cuentan con una poblaci\u00f3n en mejor estado de salud, la relaci\u00f3n no es directa, en parte por las desigualdades en la cobertura. El mejor ejemplo es Estados Unidos, que dedica la cifra m\u00e1s alta de su Producto Interior Bruto (PIB), el 16,9%, muy por delante del segundo, Suiza (12,2%), pero donde solo el 90,8% de su poblaci\u00f3n est\u00e1 cubierta por los servicios esenciales, el menor porcentaje junto al de M\u00e9xico (89,3%). Espa\u00f1a, en el otro extremo, destaca entre los pa\u00edses con mejores cifras de salud cuando su gasto se sit\u00faa ligeramente por encima de la media (8,9%, frente al 8,8%) y una cobertura del 99,9%.\n NEWSLETTER \n Recibe la mejor informaci\u00f3n en tu bandeja de entrada \nUna breve gu\u00eda para que el hombre moderno (o sea, t\u00fa) sepa c\u00f3mo regalar joyas estas navidades evitando compras fallidas de \u00faltima hora y triste desaciertos. Si ya no triunfas regalando, es porque no quieres", "date": "11/07/2019, 20:01:45", "tags": ["Esperanza vida", "OCDE", "Organizaciones internacionales", "Demograf\u00eda", "Relaciones exteriores", "Sociedad", "Salud"], "newspaper": "elpais"}