{"id": "a695bcdc-15c8-4e83-40ea-597b7043f939", "content": "El Govern se ve obligado a hacer recortes para no elevar la deuda\n\nArmengol reconoce que se est\u00e1 analizando partida por partida para ajustar las cuentas.\nEl Govern balear se ve forzado a efectuar recortes ante la bajada de ingresos y los impagos de Madrid para no aumentar la deuda, que seg\u00fan el Banco de Espa\u00f1a alcanzaba los 9.242 millones de euros en el primer trimestre del a\u00f1o. El Govern tiene un agujero de 500 millones de euros que es la suma de los 177 millones que debe el Gobierno de la naci\u00f3n a Baleares por el sistema de financiaci\u00f3n, los 180 millones del Convenio de Carreteras que presupuest\u00f3 la Comunidad Aut\u00f3noma sin que este gasto figurara en los Presupuestos Generales del Estado, y los 150 millones de menos que ha generado el descenso de la recaudaci\u00f3n. \nLa situaci\u00f3n econ\u00f3mica de Baleares fue el tema que protagoniz\u00f3 ayer la primera sesi\u00f3n del Parlament del nuevo periodo. El portavoz adjunto del PP, Antoni Costa, explic\u00f3 que en 2017 la recaudaci\u00f3n hab\u00eda bajado un 9%; en 2018, un 6,5% y en lo que llevamos de 2019, un 22%. Ha bajado sobre todo la recaudaci\u00f3n por el Impuesto de Sucesiones (12%) y el de Patrimonio (7%). Seg\u00fan Costa, \u00abcon el descenso de la recaudaci\u00f3n y el dinero que no llega de Madrid Armengol no tiene m\u00e1s remedio que, o bien realizar recortes, o subir impuestos, o elevar la deuda o dejar de pagar a los proveedores. No hay ninguna otra opci\u00f3n posible\u00bb. Costa a\u00f1adi\u00f3 que el Govern de Armengol es v\u00edctima de su propia herencia: \u00abSe ha llegado a esta situaci\u00f3n por la mala gesti\u00f3n del Pacte durante la pasada legislatura\u00bb, sentenci\u00f3 Antoni Costa. \nEl l\u00edder del PP, Biel Company, pregunt\u00f3 en la C\u00e1mara a la presidenta si, con el contexto econ\u00f3mico actual, contin\u00faa sosteniendo que \u00abBaleares est\u00e1 mejor que nunca\u00bb y afirm\u00f3 que \u00abtodas las entidades y expertos econ\u00f3micos, incluso su ministra Montero, que le ha pedido un plan de ajuste, nos est\u00e1n anunciando una importante desaceleraci\u00f3n de la econom\u00eda balear\u00bb. Company critic\u00f3 que el \u00abvicepresidente real, el se\u00f1or Negueruela, saliera a decir que la previsi\u00f3n de crecimiento del Govern es de un 2,1%, despu\u00e9s de que la AIREF anunciase que lo har\u00eda en un 1,6%\u00bb. Company le record\u00f3 a Armengol que, durante el pasado mes de agosto se han conocido datos desalentadores que afectan a Baleares como que \u00abencabezamos el mayor d\u00e9ficit de todas las autonom\u00edas y que sube el paro en agosto\u00bb. \nEn respuesta a una pregunta del portavoz del PI, Jaume Font, la presidenta Armengol reconoci\u00f3 que el Govern prepara un plan de estabilidad financiera debido a que Baleares super\u00f3 el techo de gasto de 2018. Seg\u00fan Armengol, los motivos fueron, entre otros, el pago de las sentencias judiciales de la Comunidad y el pr\u00e9stamo que tuvo que pedir la Administraci\u00f3n para hacer frente al desastre natural que tuvo lugar en la localidad de Sant Lloren\u00e7.\nFont le hab\u00eda preguntado qu\u00e9 medidas de eficiencia econ\u00f3mica pondr\u00e1 en marcha el Govern para hacer frente al desajuste econ\u00f3mico en el presupuesto de Baleares. Respecto al plan auton\u00f3mico de estabilidad financiera, Armengol explic\u00f3 que desde el Govern est\u00e1n \u00abmirando partida por partida\u00bb para poder explicar al Ministerio de Hacienda como equilibrar\u00e1n las cuentas p\u00fablicas del a\u00f1o 2019 y 2020 \u00abdesde el rigor y desde la defensa de los intereses de las Islas\u00bb. Asimismo, indic\u00f3 que este plan no afectar\u00e1 a los servicios fundamentales de los habitantes de Baleares, informa Europa Press.\nLa Consellera de Asuntos Sociales y Deportes, Fina Santiago, afirm\u00f3 que el Govern no har\u00e1 \u00ablo que har\u00eda el PP\u00bb para estabilizar la situaci\u00f3n financiera de Baleares y a\u00f1adi\u00f3 que, ante el plan de estabilidad econ\u00f3mica que prepara el Ejecutivo balear, aprovechar\u00e1n para reforzar el sistema p\u00fablico de la Administraci\u00f3n.\nEn respuesta a la diputada del PP, Margalida Duran, que pregunt\u00f3 qu\u00e9 tipo de recortes en el \u00e1mbito social ten\u00eda previsto hacer la Conselleria, Fina Santiago dijo que, ante una situaci\u00f3n as\u00ed, el PP s\u00f3lo considera la posibilidad de \u00abhacer recortes\u00bb en servicios p\u00fablicos, mientras que desde el Govern consideran que existen otras f\u00f3rmulas.\nLa sesi\u00f3n plenaria finaliz\u00f3 con el rechazo de la Proposici\u00f3n No de Ley (PNL) sobre vivienda presentada por el Grupo Parlamentario Popular, en la que se instaba al Govern a impulsar la construcci\u00f3n de \u00abun m\u00ednimo\u00bb de 8.000 viviendas de protecci\u00f3n oficial (VPO) y a implantar un 4% en el Impuesto de Transmisiones Patrimoniales, entre otros temas. La PNL, que adem\u00e1s conten\u00eda \u00abinstar a las fuerzas pol\u00edticas con representaci\u00f3n parlamentaria\u00bb a modificar las normas contra la ocupaci\u00f3n ilegal, cont\u00f3 con enmiendas del PI y Ciudadanos. Se aceptaron algunas enmiendas pero la propuesta result\u00f3 rechazada.\nConforme a los criterios deThe Trust Project\nEl director de El Mundo selecciona las noticias de mayor inter\u00e9s para ti.\n\nPor fin parece que se han dado cuenta de que gastar lo que no tienes es malo, muy malo. Eso de quedar bien con el dinero de los dem\u00e1s es muy bonito, hasta que llega el fin de mes y llegan las facturas. Pero es t\u00edpica mentalidad de izquierdas, gastar y gastar como si no hubiera un ma\u00f1ana. Lo malo de esto es que alguien tendr\u00e1 que pagar, y no ser\u00e1n ellos.", "date": "09/11/2019, 19:01:45", "tags": null, "newspaper": "elmundo"}