{"id": "b12b44ba-5f1a-4ab8-7605-a9f9df43894b", "content": "Heridas abiertas\n\nEn nuestra Guerra Civil, los dos bandos cometieron barbaridades, pero creo que la Ley de Memoria Hist\u00f3rica habla de los asesinatos de Estado que cometi\u00f3 el Gobierno ilegal de Franco cuando estaba en el poder. Cuando la derecha dice que no hay que abrir heridas, omite que un bando siempre las ha tenido y a d\u00eda de hoy nadie las ha cerrado.\nMiguel Rabad\u00e1n Soriano. Barcelona\nPuedes seguir EL PA\u00cdS Opini\u00f3n en Facebook, Twitter o suscribirte aqu\u00ed a la Newsletter.\n NEWSLETTER \n Recibe el bolet\u00edn de Opini\u00f3n \nUna breve gu\u00eda para que el hombre moderno (o sea, t\u00fa) sepa c\u00f3mo regalar joyas estas navidades evitando compras fallidas de \u00faltima hora y triste desaciertos. Si ya no triunfas regalando, es porque no quieres", "date": "10/09/2019, 19:01:45", "tags": ["Ley Memoria Hist\u00f3rica", "Guerra civil espa\u00f1ola", "Franquismo", "Legislaci\u00f3n espa\u00f1ola", "Fascismo", "Dictadura", "Ultraderecha", "Historia contempor\u00e1nea", "Ideolog\u00edas", "Historia", "Pol\u00edtica", "Legislaci\u00f3n", "Justicia"], "newspaper": "elpais"}