{"id": "b9475259-bb4a-4d9f-64fa-f595cf10ab47", "content": "El culebr\u00f3n no acaba en La Rioja: Andreu elige a una consejera diferente a la que hab\u00eda designado Podemos\n\nLa nueva presidenta elige consejera por Podemos a una diputada enfrentada a la direcci\u00f3n del partido 'morado'\nLa \u00fanica diputada de Podemos La Rioja, Raquel Romero, es la consejera de Participaci\u00f3n, Derechos Humanos y Cooperaci\u00f3n en el Gobierno riojano de coalici\u00f3n que lidera la socialista Concha Andreu, que divide as\u00ed a\u00fan m\u00e1s a su socio de Gobierno regional.\nAndreu, quien tom\u00f3 posesi\u00f3n de su cargo este jueves, dio a conocer la composici\u00f3n y estructura de su Gobierno, formado por PSOE y Podemos-Equo, con el apoyo externo de IU, que es paritario y en el que la formaci\u00f3n morada ocupa una de las nueve Consejer\u00edas.\nEl pasado 24 de agosto, el Equipo T\u00e9cnico de Podemos La Rioja, \u00f3rgano de direcci\u00f3n del partido morado en esta regi\u00f3n, design\u00f3 como consejera a la secretaria del Grupo Municipal de Unidas Podemos en Logro\u00f1o, Nazaret Mart\u00edn, pero anoche comunic\u00f3 que \u00e9sta renunciaba a formar parte del Gobierno regional \u00abal no poder conciliar su vida personal, familiar y laboral\u00bb.\nEl Equipo T\u00e9cnico, en una reuni\u00f3n extraordinaria celebrada una hora antes de la toma de posesi\u00f3n de Andreu, propuso a Amalia Revuelta, funcionaria de la Consejer\u00eda de Hacienda del Gobierno regional, como consejera en representaci\u00f3n de Podemos, lo que deb\u00eda ser ratificado por la nueva presidenta del Ejecutivo riojano.\nSin embargo, Romero se\u00f1al\u00f3, tras el acto de la toma de posesi\u00f3n, que ella no daba validez a esa reuni\u00f3n del Equipo T\u00e9cnico y que se hab\u00eda convocado \u00aba sabiendas\u00bb de que ella no pod\u00eda asistir. Finalmente, la nueva presidenta regional dio a conocer que en su gobierno estar\u00e1 Raquel Romero, y obvi\u00f3 la elecci\u00f3n por parte de la direcci\u00f3n morada de Amalia Revuelta. \n\u00abDesignar el Gobierno regional\u00bb, hab\u00eda dicho en la ma\u00f1ana de este jueves Raquel Romero, \u00abes una potestad de Concha Andreu\u00bb y \u00abentiendo que va a estar a la altura de las circunstancias\u00bb.\nPor su parte, el exsecretario general de Podemos La Rioja y miembro del Equipo T\u00e9cnico, Francisco Garrido, se\u00f1alaba que \u00absi Romero hubiera querido\u00bb, pod\u00eda haber participado en la reuni\u00f3n del Equipo T\u00e9cnico, en la que \u00abhab\u00eda quorum para adoptar decisiones\u00bb. Romero hab\u00eda indicado en los \u00faltimos d\u00edas que ella nunca ha se\u00f1alado que no quer\u00eda ser consejera, que es algo que se ha barajado desde que Podemos mantuvo las conversaciones con el PSOE para la formaci\u00f3n del Gobierno.\nConforme a los criterios deThe Trust Project\nEl director de El Mundo selecciona las noticias de mayor inter\u00e9s para ti.\n\nJajajaja, a los Podemitas les ha salido el tiro por la culata por fulleros, pronto, Raquel Romero fichar\u00e1 por el PSOE y si no, al tiempo!", "date": "09/01/2019, 19:01:45", "tags": ["Pol\u00edtica"], "newspaper": "elmundo"}