{"id": "c05ec753-10ee-442d-49e8-282a6716bb95", "content": "Zidane: \u201cEs lo que hay. Cuando miras al banquillo...\u201d\n\nFINALIZADO\nTard\u00f3 poco en empezar a llover sobre el c\u00e9sped del Santiago Bernab\u00e9u, y las primeras gotas, fr\u00edas, que se deslizaban desde la moqueta gris\u00e1cea que cubr\u00eda el cielo de Madrid, ca\u00edan sobre el cuerpo de Zinedine Zidane sin que parecieran calar en \u00e9l. Aguant\u00f3 un rato el t\u00e9cnico franc\u00e9s sin cubrirse, hasta que se puso un chubasquero corporativo negro que combinaba a la perfecci\u00f3n con su traje. En ese tiempo, el Levante meneaba la pelota por delante de los jugadores del Madrid con la misma cadencia que las gotas que adornaban la escena. Fueron 15 minutos de calma en medio de la tormenta, porque ning\u00fan jugador granota, ni su t\u00e9cnico, pens\u00f3 en que tras ese tiempo de relajaci\u00f3n se producir\u00eda una descarga de buen juego y goles por parte del Madrid. Fueron tres en 45 minutos, quiz\u00e1s el mejor acto blanco de la temporada por elaboraci\u00f3n y gusto.\n\u201cLa primera parte hemos jugado fenomenal\u201d, analiz\u00f3 Zidane. \u201cHemos tenido buen juego, goles, entrega... Al final lo que tenemos que pensar es en jugar as\u00ed los 90 minutos\u201d. Porque en m\u00e1s de hora y media es posible jugar m\u00e1s de un partido.\nRecuperado el aliento y a pesar del descuelgue de su propuesta, el Levante se mantuvo firme a su estilo. Apret\u00f3 de nuevo y logr\u00f3 un gol que tuvo efecto de sopapo. \u201cLa segunda parte tuvimos ocasiones para hacer el cuarto o m\u00e1s, pero aunque no quiero buscar excusas puede ser que f\u00edsicamente...\u201d, y ah\u00ed detuvo el tren de su respuesta Zidane. \u201cSi hubi\u00e9ramos seguido con la misma l\u00ednea de la primera mitad era un partido, con todos los respetos, para ganar cinco o seis a cero. La primera parte hemos jugado muy bien, igual la mejor que hemos jugado este a\u00f1o. Ellos han cambiado el sistema y han tenido cuatro o cinco llegadas arriba y eso nos ha complicado un poco\u201d, complet\u00f3 el discurso Courtois, salvador con una parada ante Vezo en el \u00faltimo minuto del partido.\nLos dos goles del Levante llegaron en los dos \u00fanicos remates a porter\u00eda que realizaron durante el partido, previos al cabezazo de Vezo. \u201cTen\u00eda la sensaci\u00f3n de que s\u00ed pod\u00eda llegar el empate. Ve\u00eda a los jugadores seguros de s\u00ed mismos, y eso es lo que le hace a un entrenador ser optimista\u201d, valor\u00f3 su t\u00e9cnico, Paco L\u00f3pez.\nEl primer tanto granota lo convirti\u00f3 Mayoral, cedido por el Madrid, y liberado de la famosa cl\u00e1usula del miedo que el club blanco no aplica este a\u00f1o sobre sus futbolistas. \u201cEl Real Madrid es mi vida. He estado aqu\u00ed once temporadas. No hab\u00eda forma de celebrar ese gol\u201d, explic\u00f3 el delantero. Su disparo, raso y pegado al palo, inaugur\u00f3 la reacci\u00f3n del Levante, que se vio reforzada en el momento en el que el banquillo del Madrid revolvi\u00f3 el once inicial. La salida de Casemiro fue justificada por Zidane a partir del cansancio del brasile\u00f1o, mientras que la de Ramos dej\u00f3 en el aire una molestia algo m\u00e1s preocupante: \u201cten\u00eda problemas en el s\u00f3leo\u201d, dijo el franc\u00e9s.\nCon la de Valverde ya son diez los jugadores tocados esta temporada en el Madrid, de ah\u00ed que el t\u00e9cnico haya desarrollado un miedo justificado en la p\u00e9rdida de efectivos. \u201cNo quiero que se me lesione nadie m\u00e1s, por eso no he sacado a Hazard antes. Solo lleva cuatro entrenamientos con nosotros\u201d, indic\u00f3.\nSu equipo termin\u00f3 el partido con Lucas, James y Kroos en el centro del campo. \u201cEs lo que hay. Cuando miras al banquillo... No hab\u00eda m\u00e1s posibilidades para m\u00ed de hacer otra cosa\u201d, lament\u00f3. Antes del comienzo del partido, seis de los siete suplentes eran fichajes realizados por el club esta temporada: Areola, Mendy, Jovic, Rodrygo, Militao y Hazard, solo Nacho pertenec\u00eda a la plantilla de la temporada pasada. \u201cTengo que cabrearme un poco con Hazard porque dos veces intent\u00f3 un tac\u00f3n y perdimos la pelota. Igual pensaba que ten\u00eda al defensa en su espalda\u201d, le abronc\u00f3, con una sonrisa eso s\u00ed, Courtois. \u201cVinicius tambi\u00e9n ha jugado un gran partido, a ver si para \u00e9l tambi\u00e9n llega el gol\u201d, a\u00f1adi\u00f3 el portero. El brasile\u00f1o, titular en el costado izquierdo, aunque lleg\u00f3 a intercambiarse de banda con Hazard en distintos momentos, vio como el VAR le anulaba un gol por fuera de juego. \u201cTiene 18 a\u00f1os, poco a poco\u201d, le acun\u00f3 Zizou.\nNi siquiera el mejor acto de la temporada permiti\u00f3 al Madrid convertir una lluviosa ma\u00f1ana de f\u00fatbol en un episodio agradable. No se les da bien madrugar a los blancos, aunque por fin logran llevarse la victoria en este horario. En los anteriores cinco encuentros que disput\u00f3 en su estadio entre las 12 y las 13 horas (en las pasadas dos temporadas) logr\u00f3 un empate (ante el Levante), y acumul\u00f3 cuatro derrotas (Barcelona, Levante, Girona y Betis).\nPuedes seguir Deportes de EL PA\u00cdS en Facebook, Twitter o suscribirte aqu\u00ed a la Newsletter.\n NEWSLETTER \n Recibe el bolet\u00edn de Deportes \nUna breve gu\u00eda para que el hombre moderno (o sea, t\u00fa) sepa c\u00f3mo regalar joyas estas navidades evitando compras fallidas de \u00faltima hora y triste desaciertos. Si ya no triunfas regalando, es porque no quieres", "date": "09/14/2019, 19:01:45", "tags": ["Levante UD", "Zinedine Zidane", "Liga Santander", "La Liga", "Primera divisi\u00f3n", "Real Madrid", "Ligas f\u00fatbol", "F\u00fatbol", "Equipos", "Organizaciones deportivas", "Competiciones", "Deportes"], "newspaper": "elpais"}