{"id": "d3f41944-d6da-414b-7e2a-7298dae6cc17", "content": "Uno de cada tres barceloneses declara haber sido v\u00edctima de un delito en 2018\n\nEl 31,8% de los barceloneses fue v\u00edctima de uno o m\u00e1s hechos delictivos durante 2018. La encuesta de victimizaci\u00f3n del Ayuntamiento de Barcelona, hecha p\u00fablica hoy, muestra los peores resultados desde 1983 cuando la epidemia social de la hero\u00edna castigaba la capital catalana. El balance que recoge el estudio es el peor desde el de la encuesta realizada en 1986 cuando el 26,2% de los barceloneses fue v\u00edctima de delitos. En 2017 la cifra fue de 25,6%, 6,2 puntos menos que el actual.\nEl departamento de estudios de opini\u00f3n del Consistorio entrevist\u00f3 entre el pasado 3 de junio y el 23 de julio a 1.049 personas. El 32,7% de las mujeres y el 30,8% de los hombres consultados admiti\u00f3 haber sido v\u00edctima de uno o m\u00e1s hechos delictivos durante el pasado 2018. La encuesta destaca que cada barcelon\u00e9s que se declara v\u00edctima ha sufrido una ratio de 2,7 hechos delictivos; en 2014 esta ratio de multivictimizaci\u00f3n era de 1,8. Por cada 100 barceloneses de m\u00e1s de 16 a\u00f1os se han cometido 85,7 hechos delictivos. Una cifra que hace solo cinco a\u00f1os, en 2014, era de 43,5 por cada 100 habitantes en la capital catalana.\nPor sexos, el 26,8% de las mujeres fueron v\u00edctimas de un delito que afect\u00f3 a su seguridad personal frente al 20,4% de los hombres. El 11,5% de los varones sufrieron robos en sus veh\u00edculos, el 5,1% en su casa y el 1,8% en sus negocios. En el caso de las mujeres, el 7,4% sufrieron robos en sus veh\u00edculos, el 4,2 % en sus domicilios y el 0,8% de los negocios.\nDentro de los delitos contra la seguridad personal, el m\u00e1s habitual, 9,9%, es el robo de bolso o cartera. Le sigue la tentativa de robo de bolso o cartera, 9,3%; el intento de robo de tel\u00e9fono m\u00f3vil, 4,7%; la intimidaci\u00f3n, coacci\u00f3n o amenaza, 4,3%; el robo de tel\u00e9fono m\u00f3vil, 4%, y el tir\u00f3n, con el 3,3%.\n\u00bfEn qu\u00e9 lugares se cometen los hechos delictivos? Dentro de los delitos que la encuesta clasifica como \u201ccontra la seguridad personal\u201d, el 23,8% apunta que se cometieron en calles transitadas; el 14,8% en v\u00edas con poca gente; el 3,8% en plazas, el 3,3% en parques o descampados y el 2,3%, en playas. Cuando los delitos se perpetran en establecimientos p\u00fablicos, el 4,2% fueron cometidos en bares o restaurantes, el 2,7% en centros comerciales o tiendas y el 0,5% en mercadillos.\nOtro grupo importante de delitos son los que se cometen en el transporte p\u00fablico, especialmente los robos. Seg\u00fan las respuestas, el 20,1% de ellos se produjeron en los vest\u00edbulos, en los andenes de metro y estaciones de Renfe y FFCC, o en las escaleras. El 12,2% de esos asaltos tuvieron lugar durante el trayecto. Del total de los actos delictivos en transporte p\u00fablico, el 11,3% fueron en l\u00edneas de autob\u00fas. Y en el caso del metro, las estaciones donde se cometieron m\u00e1s asaltos fueron Lesseps de la L3, Jaume I de la L4 y Collblanc de la L5.\nLa mayor\u00eda de las v\u00edctimas, el 81,9%, no conoc\u00edan a la persona agresora. En el 5,2% el agresor fue su pareja o expareja y en el 9,1% era un vecino o vecina del barrio. S\u00f3lo el 18,4% de los hechos delictivos fueron denunciados. Las v\u00edctimas que no pusieron los hechos en conocimiento de la justicia alegaron diferentes motivos: El 71,1% no denunci\u00f3 al entender que la \u201cpolic\u00eda puede hacer poca cosa\u201d, el 60,7% \u201cconf\u00eda poco en la justicia\u201d y el 40,7% \u201cconf\u00eda poco en la polic\u00eda\u201d.\nLa mayor\u00eda de entrevistados en la encuesta de victimizaci\u00f3n, el 46,9%, considera que desde 2015 (cuando Ada Colau fue proclamada alcaldesa) hasta hoy la seguridad en la ciudad ha empeorado. El 34,7% cree que sigue igual y el 8,9% cree que ha mejorado.\nA principios de este octubre se public\u00f3 la encuesta de servicios municipales 2019 que ya destacaba que la inseguridad se dispara como el problema m\u00e1s grave en Barcelona. El 17% de los ciudadanos respondieron que la falta de seguridad es el mayor problema de la capital catalana. Adem\u00e1s, el bar\u00f3metro trimestral del Consistorio tambi\u00e9n apunt\u00f3 la inseguridad como el principal problema.\n NEWSLETTER \n Recibe la mejor informaci\u00f3n en tu bandeja de entrada \nUna breve gu\u00eda para que el hombre moderno (o sea, t\u00fa) sepa c\u00f3mo regalar joyas estas navidades evitando compras fallidas de \u00faltima hora y triste desaciertos. Si ya no triunfas regalando, es porque no quieres", "date": "10/15/2019, 19:01:45", "tags": ["Robos", "Seguridad ciudadana", "Encuestas", "Barcelona", "Opini\u00f3n p\u00fablica", "Catalu\u00f1a", "Delitos", "Espa\u00f1a", "Sociedad", "Justicia"], "newspaper": "elpais"}