{"id": "ed34bf05-b1ab-455f-60cb-d8607e7439e7", "content": "Juego de tronos en la civilizaci\u00f3n de las hormigas\n\nSi usted ve una hormiga perdida por casa lo m\u00e1s probable es que la aplaste con el dedo pulgar, sin preguntarse nada m\u00e1s all\u00e1: al fin y al cabo, es solo una hormiga. Pero hay personas para las que una hormiga es un mundo y, si es rara, hasta un tesoro. \u201cLas hormigas son la civilizaci\u00f3n m\u00e1s antigua que existe, tiene 128 millones de a\u00f1os, mucho m\u00e1s que la civilizaci\u00f3n humana\u201d, explica Jos\u00e9 Antonio C\u00e1ceres, uno de los coordinadores del grupo de aficionados Tecnohormigas, que se re\u00fane cada mi\u00e9rcoles en MediaLab Prado para hablar de estos bichos prodigiosos, construir hormigueros y observarlos.\n\u00bfSon tan civilizadas? \u201cLas hormigas pastorean pulgones, por ejemplo, les llevan a alimentarse a las partes m\u00e1s verdes de la planta y protegen a sus reba\u00f1os de depredadores\u201d, explica el experto. A cambio, en este ejemplo de simbiosis, las hormigas se alimentan de una secreci\u00f3n azucarada del pulg\u00f3n. Como si fueran vacas, vaya. \u201cLas hormigas inventaron la ganader\u00eda, la agricultura\u2026 hasta el esclavismo\u201d, dice C\u00e1ceres, \u201cme gusta pensar que el ser humano se inspir\u00f3 en ellas para muchas invenciones. Solo les falt\u00f3 inventar Internet\u201d.\nAunque no andan tan lejos: los hormigueros son superorganismos que, de alguna forma todav\u00eda no desvelada del todo por los cient\u00edficos, se organizan de manera muy eficiente, dividiendo el trabajo y primando el bien com\u00fan, sin ni siquiera necesitar ordenes de la hormiga reina (que m\u00e1s bien se dedica a poner huevos). Tal vez esa mente colectiva es una especie de Internet hormiguil, aunque sin fake news ni anuncios. Pero el misterio contin\u00faa y hasta resulta \u00fatil. \u201cComo las hormigas se mueven en marabunta de forma perfectamente ordenada, hay quien las estudia para prevenir atascos de tr\u00e1fico\u201d, explica Mario Alves dos Santos, otro de los coordinadores.\nEn el s\u00f3tano de MediaLab los miembros de Tecnohormigas observan alrededor de una mesa la evoluci\u00f3n de sus animales. Los hormigueros que fabrican tienen dos zonas, una que simula el interior del hormiguero, y que permanece a oscuras, y otra que simula \u201cel mundo exterior\u201d, la zona de forrajeo, donde los bichos consiguen alimentos a plena luz del d\u00eda. Entre ambas puede haber un orificio o un tubo, que simula la puerta del hormiguero y que es muy transitado por las hacendosas hormigas. Las cigarras, mientras, duermen la siesta, aunque aqu\u00ed no hay ninguna. \u201cLas hormigas son admirables por su forma de trabajar, de construir, de convivir: es mucha complejidad en poco espacio\u201d, expone Alves. \u201cEstoy cuidando una especie esclavista en casa\u201d, comenta uno de los reunidos en torno a los hormigueros.\nSuena muy raro pero es que, como dec\u00edamos, las hormigas tambi\u00e9n inventaron la esclavitud. \u201cA grandes rasgos: una reina mata a la otra, usurpa su lugar y esclaviza a su hormiguero\u201d, nos explican, \u201cen la batalla las hormigas utilizan sus potentes mand\u00edbulas, aguijones, \u00e1cido, venenos muy potentes\u201d. Aunque estos animales pueden ser un ejemplo de convivencia y cooperaci\u00f3n dentro de su colonia, un ejemplo que los humanos deber\u00edamos seguir, entre unos hormigueros y otras puede haber Juego de Tronos.\nNo son mirmec\u00f3logos profesionales (as\u00ed se llaman los estudiosos de las hormigas) sino aficionados, aunque planean sacar pronto su primer art\u00edculo cient\u00edfico. El grupo de trabajo se cre\u00f3 el pasado mayo, cuando estaban buscando un lugar f\u00edsico para reunirse (\u201csaltar al mundo real\u201d desde su foro de Internet) y decidieron presentar un proyecto de ciencia ciudadana a MediaLab, ese lugar donde la gente se re\u00fane para experimentar y hacer cosas en com\u00fan. \u201cAqu\u00ed disponemos de espacios, de m\u00e1quinas como impresoras 3D, fresadoras o cortadoras l\u00e1ser, y, sobre todo, de mucha visibilidad\u201d, explica Alves.\nAhora est\u00e1n preparando una exposici\u00f3n de hormigas y hormigueros en el mismo centro. Pero en MediaLab m\u00e1s que ir a exposiciones, lo que se pretende es participar. Otros grupos de trabajo se dedican a fabricar pr\u00f3tesis con impresoras 3D (Autofabricantes), editar Wikipedia (Wikiesfera), generar Realidad Virtual, Aumentada o Mixta (Laboratorio de Realidades Sint\u00e9ticas) o recuperar y transformar prendas de ropa (Costura RE-make). Cualquier puede pasar por sus reuniones para colaborar y, en el caso de Tecnohormigas, para conocer m\u00e1s sobre el sorprendente mundo de las hormigas o colaborar en la fabricaci\u00f3n de hormigueros para escuelas o centros de d\u00eda.\nEn Espa\u00f1a hay 300 especies de hormigas, aunque en nuestros hogares, donde obtienen humedad, calor y alimento, abundan sobre todo dos: las pheidole, de color naranja, y las lasius, de color negro. \u00bfQu\u00e9 hace un aficionado si encuentra un mont\u00f3n de hormigas en la cocina? \u00bfTira de espray insecticida? \u201cMejor usamos un aspirador de hormigas. Buscamos con cuidado hasta encontrar a la reina. Una vez tienes la reina, ya tienes la colonia\u201d, concluye Alves.\nSigue con nosotros la actualidad de Madrid en Facebook, en Twitter y en nuestro Patio de Vecinos en Instagram\n NEWSLETTER \n Recibe la mejor informaci\u00f3n en tu bandeja de entrada \nUna breve gu\u00eda para que el hombre moderno (o sea, t\u00fa) sepa c\u00f3mo regalar joyas estas navidades evitando compras fallidas de \u00faltima hora y triste desaciertos. Si ya no triunfas regalando, es porque no quieres", "date": "11/03/2019, 20:01:45", "tags": ["Madrid", "Comunidad de Madrid", "Ocio", "Espa\u00f1a", "Estilo vida"], "newspaper": "elpais"}