{"id": "f4c0ee10-ad05-48e7-5b56-1a163465d10a", "content": "En plata: qu\u00e9 hay detr\u00e1s de los nombres del dinero\n\nLas veces que habr\u00e9 o\u00eddo en boca de mi madre lo de que algo \u201ces quemar el dinero\u201d. Y ahora me entero de que, en Alemania, es casi literal. Coloquialmente, se refieren al dinero como \u201ccarb\u00f3n\u201d, y uno no puede dejar de imaginarlo ardiendo en la industria. Ni evitar la idea de la riqueza y la destrucci\u00f3n que genera desde la revoluci\u00f3n industrial.\nEl dinero no solo se quema sino que, en nuestro mundo de palabras, tambi\u00e9n se come. Al menos en Francia, claro. Hasta hace unos pocos a\u00f1os, era habitual decir \u201cpatatas\u201d para hablar de dinero. Tambi\u00e9n \u201cmantequilla\u201d ha sido un sin\u00f3nimo popular de esta riqueza vista como inseparable de la tierra y de los combustibles que nos mantienen andando.\nSi las cosas van bien, en realidad tambi\u00e9n nosotros \u201cnos ganamos el pan\u201d, mientras que los anglosajones, directamente, son ganadores del pan o breadwinners. Y a\u00fan pagamos con \u201dpavos\u201d, por la correspondencia que hubo anta\u00f1o entre una moneda de cinco pesetas y lo que costaba comprar uno. \u00bfAlguien m\u00e1s tambi\u00e9n ha calculado, de peque\u00f1o, su paga en los helados que se pod\u00eda comer?\n\u00bfRefleja el dinero la econom\u00eda real o tambi\u00e9n demasiada especulaci\u00f3n para hacer m\u00e1s dinero con el dinero?\nMejor terminamos, porque el tan fr\u00edo dinero nos podr\u00eda llevar a un viaje infinito por casi todos los rincones de la vida. Resulta que tambi\u00e9n nos cubre, para no congelarnos, sin necesidad de at\u00e1rnoslo al cuerpo como en El lobo de Wall Street. Porque, a veces, es \u201clana\u201d o simplemente \u201ctela\u201d y, s\u00ed, unos tienen m\u00e1s para cortar que otros.\n\u00bfCurioso? S\u00ed, pero tal vez tambi\u00e9n algo m\u00e1s. \u00bfQu\u00e9 tiene que ver hoy el dinero con el carb\u00f3n, los pavos o la lana? \u00bfRefleja el dinero la econom\u00eda real que cada uno crea con el sudor de su frente, o tambi\u00e9n demasiada especulaci\u00f3n para hacer m\u00e1s dinero con el dinero?\nEsta es una de las reflexiones a las que nos llama el D\u00eda mundial de la banca con valores (7 de noviembre), organizado por una alianza internacional de casi 60 bancos que se han propuesto financiar solo proyectos que generen beneficio real para la sociedad. O, dicho de otra manera, no hacer juegos de manos para engrosar sus balances y, de vez en cuando, provocar inesperadas turbulencias que acaban pagando otros.\nPor supuesto, muchas otras iniciativas se plantean tambi\u00e9n esta idea, como los promotores de nuevas monedas sociales vinculadas a compra en comercio local y que, por tanto, quieren ligar el dinero a una econom\u00eda m\u00e1s comprensible y claramente provechosa para toda la ciudadan\u00eda.\nHemos inventado nombres para el dinero y tambi\u00e9n podemos reinventar su funci\u00f3n social, como creaci\u00f3n humana que es. Hablemos en plata.\n NEWSLETTER \n Recibe la mejor informaci\u00f3n en tu bandeja de entrada \nUna breve gu\u00eda para que el hombre moderno (o sea, t\u00fa) sepa c\u00f3mo regalar joyas estas navidades evitando compras fallidas de \u00faltima hora y triste desaciertos. Si ya no triunfas regalando, es porque no quieres", "date": "10/31/2019, 20:01:45", "tags": ["Banca \u00e9tica", "Dinero", "Medios de pago", "Banca", "Finanzas"], "newspaper": "elpais"}